purger/__init__.py
purger/main.py
fork_purger-21.1.3.dist-info/LICENSE
fork_purger-21.1.3.dist-info/METADATA
fork_purger-21.1.3.dist-info/WHEEL
fork_purger-21.1.3.dist-info/entry_points.txt
fork_purger-21.1.3.dist-info/top_level.txt
fork_purger-21.1.3.dist-info/RECORD
