Metadata-Version: 2.1
Name: fork-purger
Version: 21.1.3
Summary: Delete all of your forked repositories on Github.
Home-page: https://github.com/rednafi/fork-purger
Author: Redowan Delowar
Author-email: redowan.nafi@gmail.com
License: MIT
Platform: UNKNOWN
Classifier: License :: OSI Approved :: MIT License
Classifier: Programming Language :: Python :: 3
Classifier: Programming Language :: Python :: 3 :: Only
Classifier: Programming Language :: Python :: 3.8
Classifier: Programming Language :: Python :: 3.9
Classifier: Programming Language :: Python :: 3.10
Classifier: Programming Language :: Python :: Implementation :: CPython
Requires-Python: >=3.8.0
License-File: LICENSE
Requires-Dist: click (>=7)
Requires-Dist: httpx[http2] (>=0.16.0)
Provides-Extra: dev_deps
Requires-Dist: black ; extra == 'dev_deps'
Requires-Dist: flake8 ; extra == 'dev_deps'
Requires-Dist: isort ; extra == 'dev_deps'
Requires-Dist: mypy ; extra == 'dev_deps'
Requires-Dist: pytest ; extra == 'dev_deps'
Requires-Dist: pytest-asyncio ; extra == 'dev_deps'
Requires-Dist: pytest-coverage ; extra == 'dev_deps'
Requires-Dist: twine ; extra == 'dev_deps'
